Combinational Circuits/Arthimetic And logical/Full_adder/Full_adder.v
module Full_adder(A,B,C,Sum,Carry);
	input A,B,C;
	output Sum,Carry;
	wire w1,w2,w3;

xor a1 (w1,A,B);
xor a2 (Sum,C,w1);

and a3 (w2,w1,C);
and a4 (w3,A,B);

or a5 (Carry,w2,w3);

endmodule

Combinational Circuits/Full_adder/FA_tb.v
module FA_tb();

reg A,B,C;
wire Sum,Carry;

Full_adder dut (.A(A), .B(B), .C(C), .Sum(Sum), .Carry(Carry));

initial begin
 $dumpfile("FA_tb.vcd");
 $dumpvars(0,FA_tb);
end

initial begin


$monitor("time=%t,A=%b,B=%b,C=%b,Sum=%b,Carry=%b",$time,A,B,C,Sum,Carry);

#2 A=1'b0; B=1'b0; C=1'b0;
#2 A=1'b0; B=1'b0; C=1'b1;
#2 A=1'b0; B=1'b1; C=1'b0;
#2 A=1'b0; B=1'b1; C=1'b1;
#2 A=1'b1; B=1'b0; C=1'b0;
#2 A=1'b1; B=1'b0; C=1'b1;
#2 A=1'b1; B=1'b1; C=1'b0;
#2 A=1'b1; B=1'b1; C=1'b1;

end
endmodule

Combinational Circuits/Full_adder/FA_tb.vcd
$date
	Sun Jul 05 00:30:29 2026
$end
$version
	Icarus Verilog
$end
$timescale
	1s
$end
$scope module FA_tb $end
$var wire 1 ! Sum $end
$var wire 1 " Carry $end
$var reg 1 # A $end
$var reg 1 $ B $end
$var reg 1 % C $end
$scope module dut $end
$var wire 1 # A $end
$var wire 1 $ B $end
$var wire 1 % C $end
$var wire 1 " Carry $end
$var wire 1 ! Sum $end
$var wire 1 & w1 $end
$var wire 1 ' w2 $end
$var wire 1 ( w3 $end
$upscope $end
$upscope $end
$enddefinitions $end
$comment Show the parameter values. $end
$dumpall
$end
#0
$dumpvars
x(
x'
x&
x%
x$
x#
x"
x!
$end
#2
0"
0!
0'
0&
0(
0%
0$
0#
#4
1!
1%
#6
1&
0%
1$
#8
1"
0!
1'
1%
#10
0"
1!
0'
0%
0$
1#
#12
1"
0!
1'
1%
#14
0'
0&
1(
0%
1$
#16
1!
1%
