Combinational Circuits/Data Routing/Decode_FA/decoder.v
module decoder(enable,in,y);
    input enable;
    input [2:0]in;
    output reg [7:0]y;


    always@(*) begin
        
         case(in)
         default : y=8'b00000000;
         3'b000 : y=8'b00000001;
         3'b001 : y=8'b00000010;
         3'b010 : y=8'b00000100;
         3'b011 : y=8'b00001000;
         3'b100 : y=8'b00010000;
         3'b101 : y=8'b00100000;
         3'b110 : y=8'b01000000;
         3'b111 : y=8'b10000000;

         endcase
    end
endmodule

Combinational Circuits/Data Routing/Decode_FA/decoder_tb.v
module decode_tb();
reg [2:0]in;
reg enable;
wire [7:0]y;

decoder dut (.in(in),.enable(enable),.y(y));

initial begin
    $dumpfile("decode_tb.vcd");
    $dumpvars(0,decode_tb);


    $monitor("Time=%t Enable=%b INPUT=%b OUTPUT=%b ",$time,enable,in,y);

enable=1'b1;
#10;
    in = 3'b000;#10;
    in = 3'b001;#10; 
    in = 3'b010;#10;
    in = 3'b011;#10;
    in = 3'b100;#10;
    in = 3'b101;#10;
    in = 3'b110;#10;
    in = 3'b111;#10;
    $finish;
end
endmodule

Combinational Circuits/Data Routing/Decode_FA/decode_tb.vcd
$date
	Sat Aug 15 15:08:10 2026
$end
$version
	Icarus Verilog
$end
$timescale
	1s
$end
$scope module decode_tb $end
$var wire 8 ! y [7:0] $end
$var reg 1 " enable $end
$var reg 3 # in [2:0] $end
$scope module dut $end
$var wire 1 " enable $end
$var wire 3 $ in [2:0] $end
$var reg 8 % y [7:0] $end
$upscope $end
$upscope $end
$enddefinitions $end
$comment Show the parameter values. $end
$dumpall
$end
#0
$dumpvars
bx %
bx $
bx #
1"
bx !
$end
#10
b1 !
b1 %
b0 #
b0 $
#20
b10 !
b10 %
b1 #
b1 $
#30
b100 !
b100 %
b10 #
b10 $
#40
b1000 !
b1000 %
b11 #
b11 $
#50
b10000 !
b10000 %
b100 #
b100 $
#60
b100000 !
b100000 %
b101 #
b101 $
#70
b1000000 !
b1000000 %
b110 #
b110 $
#80
b10000000 !
b10000000 %
b111 #
b111 $
