Combinational Circuits/Arthimetic And logical/Full_subtractor/Full_subtractor.v
module Full_subtractor(A,B,C,Dif,Borr);

input A,B,C;
output Dif,Borr;

assign Dif=A^B^C;
assign Borr=~A&(B^C)|B&C;

endmodule

Combinational Circuits/Full_subtractor/FS_tb.v
module FS_tb();

reg A,B,C; //Defining input as register
wire Dif,Borr; //Defining output as wire

Full_subtractor DUT(.A(A),.B(B),.C(C),.Dif(Dif),.Borr(Borr));// instantiation of Full_subtractor 

initial begin
	$dumpfile("FS_tb.vcd");
	$dumpvars(0,FS_tb);
end

//all posssible inputs for 3 bit is given 
initial begin

$monitor("time=%t,A=%b,B=%b,C=%b,Dif=%b,Borr=%b",$time,A,B,C,Dif,Borr);

#2 A=1'b0; B=1'b0; C=1'b0;
#2 A=1'b0; B=1'b0; C=1'b1;
#2 A=1'b0; B=1'b1; C=1'b0;
#2 A=1'b0; B=1'b1; C=1'b1;
#2 A=1'b1; B=1'b0; C=1'b0;
#2 A=1'b1; B=1'b0; C=1'b1;
#2 A=1'b1; B=1'b1; C=1'b0;
#2 A=1'b1; B=1'b1; C=1'b1;

end
endmodule

Combinational Circuits/Full_subtractor/FS_tb.vcd
$date
	Sun Jul 05 11:24:57 2026
$end
$version
	Icarus Verilog
$end
$timescale
	1s
$end
$scope module FS_tb $end
$var wire 1 ! Dif $end
$var wire 1 " Borr $end
$var reg 1 # A $end
$var reg 1 $ B $end
$var reg 1 % C $end
$scope module DUT $end
$var wire 1 # A $end
$var wire 1 $ B $end
$var wire 1 " Borr $end
$var wire 1 % C $end
$var wire 1 ! Dif $end
$upscope $end
$upscope $end
$enddefinitions $end
$comment Show the parameter values. $end
$dumpall
$end
#0
$dumpvars
x%
x$
x#
x"
x!
$end
#2
0"
0!
0%
0$
0#
#4
1"
1!
1%
#6
0%
1$
#8
0!
1%
#10
0"
1!
0%
0$
1#
#12
0!
1%
#14
0%
1$
#16
1"
1!
1%
