Combinational Circuits/Data Routing/Decode_FA/decoder.v
module decoder(enable,in,y);
    input enable;
    input [2:0]in;
    output reg [7:0]y;


    always@(*) begin
        
         case(in)
         default : y=8'b00000000;
         3'b000 : y=8'b00000001;
         3'b001 : y=8'b00000010;
         3'b010 : y=8'b00000100;
         3'b011 : y=8'b00001000;
         3'b100 : y=8'b00010000;
         3'b101 : y=8'b00100000;
         3'b110 : y=8'b01000000;
         3'b111 : y=8'b10000000;

         endcase
    end
endmodule

Combinational Circuits/Arthimetic And logical/FA_Decode/FA_Decode.v
`include "..\Data Routing\Decode_FA\decoder.v"
module FA_Decode(A,B,Cin,Sum,Carry);

    input A,B,Cin;
    output Sum,Carry;

wire [7:0]out;
    decoder dut(.in({A,B,Cin}),.enable(1'b1),.y(out));

assign Sum = out[1] |out[2] |out[4] |out[7];
assign Carry= out[3] |out[5] |out[6] |out[7]; 
// or g1(Sum,y[1],y[2],y[4],y[7]);
// or g2(Carry,y[3],y[5],y[6],y[7]);

endmodule

Combinational Circuits/Arthimetic And logical/FA_Decode/FA_Decode_tb.v
module FA_Decode_tb();

reg A,B,Cin;
wire Sum,Carry;

FA_Decode dut (.A(A), .B(B), .Cin(Cin), .Sum(Sum), .Carry(Carry));

initial begin
 $dumpfile("FA_Decode_tb.vcd");
 $dumpvars(0,FA_Decode_tb);
end

initial begin


$monitor("time=%t,A=%b,B=%b,C=%b,Sum=%b,Carry=%b",$time,A,B,Cin,Sum,Carry);

#10 A=1'b0; B=1'b0; Cin=1'b0;
#10 A=1'b0; B=1'b0; Cin=1'b1;
#10 A=1'b0; B=1'b1; Cin=1'b0;
#10 A=1'b0; B=1'b1; Cin=1'b1;
#10 A=1'b1; B=1'b0; Cin=1'b0;
#10 A=1'b1; B=1'b0; Cin=1'b1;
#10 A=1'b1; B=1'b1; Cin=1'b0;
#10 A=1'b1; B=1'b1; Cin=1'b1;

end
endmodule

Combinational Circuits/Arthimetic And logical/FA_Decode/FA_Decode_tb.vcd
$date
	Sat Aug 15 19:44:16 2026
$end
$version
	Icarus Verilog
$end
$timescale
	1s
$end
$scope module FA_Decode_tb $end
$var wire 1 ! Sum $end
$var wire 1 " Carry $end
$var reg 1 # A $end
$var reg 1 $ B $end
$var reg 1 % Cin $end
$scope module dut $end
$var wire 1 # A $end
$var wire 1 $ B $end
$var wire 1 " Carry $end
$var wire 1 % Cin $end
$var wire 1 ! Sum $end
$var wire 8 & out [7:0] $end
$scope module dut $end
$var wire 1 ' enable $end
$var wire 3 ( in [2:0] $end
$var reg 8 ) y [7:0] $end
$upscope $end
$upscope $end
$upscope $end
$enddefinitions $end
$comment Show the parameter values. $end
$dumpall
$end
#0
$dumpvars
bx )
bx (
1'
bx &
x%
x$
x#
x"
x!
$end
#10
0"
0!
b1 &
b1 )
0%
0$
b0 (
0#
#20
1!
b10 &
b10 )
b1 (
1%
#30
b100 &
b100 )
0%
b10 (
1$
#40
1"
0!
b1000 &
b1000 )
b11 (
1%
#50
0"
1!
b10000 &
b10000 )
0%
0$
b100 (
1#
#60
1"
0!
b100000 &
b100000 )
b101 (
1%
#70
b1000000 &
b1000000 )
0%
b110 (
1$
#80
1!
b10000000 &
b10000000 )
b111 (
1%
